eventsender/__init__.py
eventsender/event_sender.py
cs_eventsender-0.0.6.dist-info/METADATA
cs_eventsender-0.0.6.dist-info/WHEEL
cs_eventsender-0.0.6.dist-info/top_level.txt
cs_eventsender-0.0.6.dist-info/RECORD
