Metadata-Version: 2.1
Name: cs-eventsender
Version: 0.0.6
Summary: A package for sending event notifications.
Author: Richard
Author-email: <rich_swainson@hotmail.co.uk>
Keywords: binance,api,wrapper,c2c,sapi
Classifier: Development Status :: 5 - Production/Stable
Classifier: Intended Audience :: Developers
Classifier: Programming Language :: Python :: 3
Classifier: Operating System :: Unix
Classifier: Operating System :: MacOS :: MacOS X
Classifier: Operating System :: Microsoft :: Windows
Requires-Dist: requests
Requires-Dist: cs-telegram-bot-api
